{
   "name": "",
   "author": "",
   "category": 6,
   "ingredients": [
      {
         "amount": 1,
         "name": ""
      },
      {
         "amount": 2,
         "name": ""
      },
      {
         "amount": 1,
         "name": ""
      },
      {
         "amount": 2,
         "name": ""
      },
      {
         "amount": 1,
         "name": ""
      },
      {
         "amount": 2,
         "name": ""
      },
      {
         "amount": 1,
         "name": ""
      },
      {
         "amount": 2,
         "name": ""
      },
      {
         "amount": 1,
         "name": ""
      },
      {
         "amount": 2,
         "name": ""
      },
      {
         "amount": 1,
         "name": ""
      },
      {
         "amount": 2,
         "name": ""
      },
      {
         "amount": 1,
         "name": ""
      },
      {
         "amount": 2,
         "name": ""
      },
      {
         "amount": 1,
         "name": ""
      },
      {
         "amount": 2,
         "name": ""
      },
      {
         "amount": 3,
         "name": ""
      }
   ],
   "instructions": "",
   "yield": {
      "amount": 0,
      "name": ""
   }
}
