{
   "name": "Peanut Butter No-Bake Cookies",
   "author": "Becky Collier",
   "category": 6,
   "ingredients": [
      {
         "amount": 0.5,
         "name": "cup Peanut Butter"
      },
      {
         "amount": 0.5,
         "name": "cups butter"
      },
      {
         "amount": 2,
         "name": "cups sugar"
      },
      {
         "amount": 0.5,
         "name": "cup cold milk"
      },
      {
         "amount": 3.5,
         "name": "cups quick cooking oats"
      },
      {
         "amount": 1,
         "name": "tbsp vanilla"
      }
   ],
   "instructions": "Add butter, sugar and milk to a heavy bottom pot, bring to a boil (rolling) and boil for 1 min while stirring. Remove pot from heat & mix in your peanut butter, Vanilla & oats. Use spoon to scoop and drop mixture on parchment paper and let cool.",
   "yield": {
      "amount": 0,
      "name": ""
   }
}
